{
  "db_name": "PostgreSQL",
  "query": "\n            INSERT INTO \n                mints (user_id, asset_id, amount)\n            VALUES\n                ($1, $2, $3::fraction)\n            ",
  "describe": {
    "columns": [],
    "parameters": {
      "Left": [
        "Uuid",
        "Uuid",
        {
          "Custom": {
            "name": "fraction",
            "kind": {
              "Composite": [
                [
                  "numer",
                  "Numeric"
                ],
                [
                  "denom",
                  "Numeric"
                ]
              ]
            }
          }
        }
      ]
    },
    "nullable": []
  },
  "hash": "4b0f9a88e4b771e21c206379f232ec00dfba5837a651b9d8ec9bdf240f54d750"
}
