{
  "db_name": "PostgreSQL",
  "query": "\n            SELECT\n                id,\n                created_at,\n                last_modification_at,\n                quote_asset_id,\n                base_asset_id,\n                kind as \"kind: CandlestickType\",\n                topen,\n                tclose,\n                open as \"open: Fraction\",\n                high as \"high: Fraction\",\n                low as \"low: Fraction\",\n                close as \"close: Fraction\",\n                span,\n                taker_quote_volume as \"taker_quote_volume: Fraction\",\n                taker_base_volume as \"taker_base_volume: Fraction\",\n                maker_quote_volume as \"maker_quote_volume: Fraction\",\n                maker_base_volume as \"maker_base_volume: Fraction\"\n            FROM spot.candlesticks\n            WHERE spot.candlesticks.quote_asset_id = $1 AND spot.candlesticks.base_asset_id = $2\n            AND spot.candlesticks.topen = $3 AND spot.candlesticks.tclose = $4\n            ",
  "describe": {
    "columns": [
      {
        "ordinal": 0,
        "name": "id",
        "type_info": "Uuid"
      },
      {
        "ordinal": 1,
        "name": "created_at",
        "type_info": "Timestamptz"
      },
      {
        "ordinal": 2,
        "name": "last_modification_at",
        "type_info": "Timestamptz"
      },
      {
        "ordinal": 3,
        "name": "quote_asset_id",
        "type_info": "Uuid"
      },
      {
        "ordinal": 4,
        "name": "base_asset_id",
        "type_info": "Uuid"
      },
      {
        "ordinal": 5,
        "name": "kind: CandlestickType",
        "type_info": {
          "Custom": {
            "name": "candlestick_type",
            "kind": {
              "Enum": [
                "interval",
                "tick"
              ]
            }
          }
        }
      },
      {
        "ordinal": 6,
        "name": "topen",
        "type_info": "Timestamptz"
      },
      {
        "ordinal": 7,
        "name": "tclose",
        "type_info": "Timestamptz"
      },
      {
        "ordinal": 8,
        "name": "open: Fraction",
        "type_info": {
          "Custom": {
            "name": "fraction",
            "kind": {
              "Composite": [
                [
                  "numer",
                  "Numeric"
                ],
                [
                  "denom",
                  "Numeric"
                ]
              ]
            }
          }
        }
      },
      {
        "ordinal": 9,
        "name": "high: Fraction",
        "type_info": {
          "Custom": {
            "name": "fraction",
            "kind": {
              "Composite": [
                [
                  "numer",
                  "Numeric"
                ],
                [
                  "denom",
                  "Numeric"
                ]
              ]
            }
          }
        }
      },
      {
        "ordinal": 10,
        "name": "low: Fraction",
        "type_info": {
          "Custom": {
            "name": "fraction",
            "kind": {
              "Composite": [
                [
                  "numer",
                  "Numeric"
                ],
                [
                  "denom",
                  "Numeric"
                ]
              ]
            }
          }
        }
      },
      {
        "ordinal": 11,
        "name": "close: Fraction",
        "type_info": {
          "Custom": {
            "name": "fraction",
            "kind": {
              "Composite": [
                [
                  "numer",
                  "Numeric"
                ],
                [
                  "denom",
                  "Numeric"
                ]
              ]
            }
          }
        }
      },
      {
        "ordinal": 12,
        "name": "span",
        "type_info": "Int8"
      },
      {
        "ordinal": 13,
        "name": "taker_quote_volume: Fraction",
        "type_info": {
          "Custom": {
            "name": "fraction",
            "kind": {
              "Composite": [
                [
                  "numer",
                  "Numeric"
                ],
                [
                  "denom",
                  "Numeric"
                ]
              ]
            }
          }
        }
      },
      {
        "ordinal": 14,
        "name": "taker_base_volume: Fraction",
        "type_info": {
          "Custom": {
            "name": "fraction",
            "kind": {
              "Composite": [
                [
                  "numer",
                  "Numeric"
                ],
                [
                  "denom",
                  "Numeric"
                ]
              ]
            }
          }
        }
      },
      {
        "ordinal": 15,
        "name": "maker_quote_volume: Fraction",
        "type_info": {
          "Custom": {
            "name": "fraction",
            "kind": {
              "Composite": [
                [
                  "numer",
                  "Numeric"
                ],
                [
                  "denom",
                  "Numeric"
                ]
              ]
            }
          }
        }
      },
      {
        "ordinal": 16,
        "name": "maker_base_volume: Fraction",
        "type_info": {
          "Custom": {
            "name": "fraction",
            "kind": {
              "Composite": [
                [
                  "numer",
                  "Numeric"
                ],
                [
                  "denom",
                  "Numeric"
                ]
              ]
            }
          }
        }
      }
    ],
    "parameters": {
      "Left": [
        "Uuid",
        "Uuid",
        "Timestamptz",
        "Timestamptz"
      ]
    },
    "nullable": [
      false,
      false,
      false,
      false,
      false,
      false,
      false,
      false,
      false,
      false,
      false,
      false,
      false,
      false,
      false,
      false,
      false
    ]
  },
  "hash": "8ef52941c1cc25a4ea25ae2ad1671c09821ea409752d5b90eeca501e6fb06626"
}
